TrimoonCam2Telegram/__init__.py
TrimoonCam2Telegram/cam2telegram_config.py
TrimoonCam2Telegram/cams/__init__.py
TrimoonCam2Telegram/cams/bongacams2telegram.py
TrimoonCam2Telegram/cams/camsoda2telegram.py
TrimoonCam2Telegram/cams/chaturbate2telegram.py
TrimoonCam2Telegram/telegram/TelegramCustom.py
TrimoonCam2Telegram/telegram/TelegramPublisher.py
TrimoonCam2Telegram/telegram/__init__.py
TrimoonCam2Telegram-0.1.dist-info/LICENSE.md
TrimoonCam2Telegram-0.1.dist-info/METADATA
TrimoonCam2Telegram-0.1.dist-info/WHEEL
TrimoonCam2Telegram-0.1.dist-info/top_level.txt
TrimoonCam2Telegram-0.1.dist-info/RECORD
