Metadata-Version: 2.1
Name: TrimoonCam2Telegram
Version: 0.1
Summary: Push Cam Affiliate links 
Home-page: https://github.com/trimoon056/TrimoonCam2Telegram
Author: Trimoon Cam 2 Telegram
Author-email: trimoon056@gmail.com
Classifier: Programming Language :: Python :: 3
Classifier: License :: OSI Approved :: MIT License
Classifier: Operating System :: OS Independent
Requires-Python: >=3.7, <3.13
License-File: LICENSE.md
Requires-Dist: Pillow
Requires-Dist: python-dotenv
Requires-Dist: sockets
Requires-Dist: pycountry
Requires-Dist: pycountry-convert
Requires-Dist: requests
